ml/__init__.py
ml/predict.py
ml/train.py
ml/data/__init__.py
ml/data/data.py
ml/data/mnist.py
ml/neural_network/__init__.py
ml/neural_network/evaluate.py
ml/neural_network/layer.py
ml/neural_network/neural_network.py
ml/neural_network/train.py
ml_lib-0.0.3.dist-info/DESCRIPTION.rst
ml_lib-0.0.3.dist-info/METADATA
ml_lib-0.0.3.dist-info/RECORD
ml_lib-0.0.3.dist-info/WHEEL
ml_lib-0.0.3.dist-info/metadata.json
ml_lib-0.0.3.dist-info/top_level.txt
scripts/__init__.py
scripts/youtube8m/__init__.py
scripts/youtube8m/train.py
tests/__init__.py
tests/test_cnn.py
tests/test_mlp.py
tools/__init__.py
tools/workers.py
