Metadata-Version: 2.0
Name: ml-lib
Version: 0.0.3
Summary: Machine learning library built on top of TensorFlow.
Home-page: https://github.com/AlassaneNdiaye/machine-learning
Author: Alassane Ndiaye
Author-email: alassane.ndiaye@gmail.com
License: UNKNOWN
Platform: UNKNOWN
Requires-Dist: numpy
Requires-Dist: tensorflow
